seyaml/__init__.py
seyaml/cli.py
seyaml/loader.py
seyaml-0.1.1.dist-info/licenses/LICENSE
seyaml-0.1.1.dist-info/METADATA
seyaml-0.1.1.dist-info/WHEEL
seyaml-0.1.1.dist-info/entry_points.txt
seyaml-0.1.1.dist-info/top_level.txt
seyaml-0.1.1.dist-info/RECORD
