Metadata-Version: 2.4
Name: seyaml
Version: 0.1.1
Summary: YAML loader with support for !secret, !env, and !enc tags
Author: Pragman
Author-email: Phragman <a@staphi.com>
License: MIT
Requires-Python: >=3.7
License-File: LICENSE
Requires-Dist: PyYAML>=6.0
Requires-Dist: cryptography>=40.0
Requires-Dist: click>=8.0
Dynamic: author
Dynamic: license-file
Dynamic: requires-python
